{
  "bot": "purdyblog",
  "runs": [
    {
      "ts": "2026-07-16T16:20:11",
      "status": "ok",
      "video_id": "vO982Mh6Fbw",
      "title": "İlyas Yalçıntaş'ın terazisi neyin nesi? #i̇lyasyalçıntaştan #shorts"
    },
    {
      "ts": "2026-07-16T18:51:38",
      "status": "ok",
      "video_id": "XfT8mQYx0nY",
      "title": "Asena Keskinci tesettüre girdi! #asenakeskinci #shorts"
    },
    {
      "ts": "2026-07-17T07:12:52",
      "status": "ok",
      "video_id": "-G0fO0D0FXs",
      "title": "Zeki Alasya'nın sırrı mı? #zekialasyanın #shorts #akasyadurağı"
    },
    {
      "ts": "2026-07-17T10:46:50",
      "status": "ok",
      "video_id": "jWA82DvFqBM",
      "title": "Edis'in 1 Milyon Dolarlık Sırrı mı? #Edis #shorts"
    },
    {
      "ts": "2026-07-17T13:56:24",
      "status": "ok",
      "video_id": "KCCamw383gE",
      "title": "Oktay Kaynarca'dan şaşırtan itiraflar! #oktaykaynarcadan #shorts #kurtlarvadisi"
    },
    {
      "ts": "2026-07-17T16:19:09",
      "status": "ok",
      "video_id": "w2uwozS_HeU",
      "title": "Halit Ergenç'in gizli çay alışkanlığı #BergüzarKorel #Shorts #Ünlüler"
    },
    {
      "ts": "2026-07-17T18:48:07",
      "status": "ok",
      "video_id": "v_MsPc77vIE",
      "title": "Boşanmak bu kadar pahalı mı? #shorts #boşanma"
    },
    {
      "ts": "2026-07-18T06:56:58",
      "status": "ok",
      "video_id": "Ui_EIVhKIgY",
      "title": "Yavuz Bingöl Acil Ameliyata Alındı! #yavuzbingölden #shorts"
    },
    {
      "ts": "2026-07-18T10:18:06",
      "status": "ok",
      "video_id": "9ioD1JohQUc",
      "title": "Ayşenur Balcı Cezaevinde! #ayşenurbalcı #shorts #uyusturucusoruşturması"
    },
    {
      "ts": "2026-07-18T13:39:37",
      "status": "ok",
      "video_id": "F13dwhBu_CY",
      "title": "Mehmed: Fetihler Sultanı dizisi neden Çin'i kızdırıyor? #mehmedfetihlersultanı #"
    },
    {
      "ts": "2026-07-18T16:01:13",
      "status": "ok",
      "video_id": "S4pHz9OimoI",
      "title": "Muhammed Cangören'in Gizli Hayatı #muhammedcangören #shorts"
    },
    {
      "ts": "2026-07-18T18:41:53",
      "status": "ok",
      "video_id": "Urbx34Yapns",
      "title": "Mahmut Orhan İç Çamaşırı Tezgahına Ne Yaptı? #mahmutorhan #shorts"
    },
    {
      "ts": "2026-07-19T07:24:07",
      "status": "ok",
      "video_id": "X6_bPCJy2p8",
      "title": "82 yaşında mayoda! #nebahatçehreden #shorts"
    },
    {
      "ts": "2026-07-19T10:27:20",
      "status": "ok",
      "video_id": "dDrXcw262zk",
      "title": "Evliyken yasak aşk mı? #shorts #İhanetSkandalı"
    },
    {
      "ts": "2026-07-19T13:42:14",
      "status": "ok",
      "video_id": "tF0Yn7cPPsI",
      "title": "Fatma Soydaş'ın Öpüşme Görüntüsü Gerçek Mi? #fatmasoydaşın #shorts"
    },
    {
      "ts": "2026-07-19T16:01:14",
      "status": "ok",
      "video_id": "t7G5-XRspDE",
      "title": "Neslihan Atagül ilk kez konuştu! #neslihanatagülden #shorts"
    },
    {
      "ts": "2026-07-19T18:44:18",
      "status": "ok",
      "video_id": "RuSWwXAmdLk",
      "title": "Cem Yılmaz'ın kuzeni neden gözaltına alındı? #cemyılmazın #shorts #soruşturma"
    },
    {
      "ts": "2026-07-20T07:54:08",
      "status": "ok",
      "video_id": "xOX4N92UoOQ",
      "title": "Simge Sağın ve DJ İlkay Şencan niye ayrıldı? #shorts #simgesağınındji̇lkayşencan"
    },
    {
      "ts": "2026-07-20T11:44:32",
      "status": "ok",
      "video_id": "uGO4-weICh4",
      "title": "Tyla Metroda Ne Yaptı? #shorts #Tyla"
    },
    {
      "ts": "2026-07-20T14:26:11",
      "status": "ok",
      "video_id": "7yOgHq1Rn8U",
      "title": "Katie Price'ın Evlilik Skandalı! #shorts #skandal"
    }
  ]
}